LICENSE.TXT
README.md
setup.py
rocket_youcef/__init__.py
rocket_youcef/rocket_youcef.py
rocket_youcef.egg-info/PKG-INFO
rocket_youcef.egg-info/SOURCES.txt
rocket_youcef.egg-info/dependency_links.txt
rocket_youcef.egg-info/top_level.txt