Metadata-Version: 2.1
Name: rocket_youcef
Version: 2.0.0
Summary: `rocket` is a Python library for simulating and manipulating rocket objects, including their movement and different properties.
Home-page: http://pypi.python.org/pypi/rocket_youcef/
Author: talbi_youcef
Author-email: y.talbi@esi-sba.dz
License: LICENSE.txt
License-File: LICENSE.TXT
